LICENSE
README.md
setup.py
geveze.egg-info/PKG-INFO
geveze.egg-info/SOURCES.txt
geveze.egg-info/dependency_links.txt
geveze.egg-info/entry_points.txt
geveze.egg-info/requires.txt
geveze.egg-info/top_level.txt
src/twinkle.py